devicer/__init__.py
devicer/confidence.py
devicer/hashing.py
devicer_py-0.2.0.dist-info/licenses/license.txt
devicer_py-0.2.0.dist-info/METADATA
devicer_py-0.2.0.dist-info/WHEEL
devicer_py-0.2.0.dist-info/top_level.txt
devicer_py-0.2.0.dist-info/RECORD
