Metadata-Version: 2.4
Name: devicer.py
Version: 0.2.0
Summary: Open-Source Python Middleware for Digital Fingerprinting
Author: One anonymous contributor
Author-email: Samuel Roux <sam.roux.com@gmail.com>, Stephen Perso <stephenrperso@gmail.com>
Project-URL: Homepage, https://gatewaycorporate.org/
Project-URL: Repository, https://github.com/gatewaycorporate/fp-devicer-python.git
Project-URL: Issues, https://github.com/gatewaycorporate/fp-devicer-python/issues
Keywords: fingerprinting,identification,middleware,tracking
Classifier: Development Status :: 4 - Beta
Classifier: Intended Audience :: Developers
Classifier: Programming Language :: Python :: 3
Classifier: Programming Language :: Python :: 3.8
Classifier: Programming Language :: Python :: 3.9
Classifier: Programming Language :: Python :: 3.10
Classifier: Programming Language :: Python :: 3.11
Classifier: Topic :: Software Development :: Libraries
Requires-Python: >=3.8
License-File: license.txt
Requires-Dist: py-tlsh>=4.7.2
Dynamic: license-file
